django_auth_ipwhitelist/__init__.py
django_auth_ipwhitelist/admin.py
django_auth_ipwhitelist/backends.py
django_auth_ipwhitelist/middleware.py
django_auth_ipwhitelist/models.py
django_auth_ipwhitelist/serializers.py
django_auth_ipwhitelist/settings.py
django_auth_ipwhitelist/migrations/0001_initial.py
django_auth_ipwhitelist/migrations/__init__.py
django_auth_ipwhitelist-0.1.0.dist-info/AUTHORS.rst
django_auth_ipwhitelist-0.1.0.dist-info/LICENSE
django_auth_ipwhitelist-0.1.0.dist-info/METADATA
django_auth_ipwhitelist-0.1.0.dist-info/WHEEL
django_auth_ipwhitelist-0.1.0.dist-info/top_level.txt
django_auth_ipwhitelist-0.1.0.dist-info/RECORD
