Metadata-Version: 2.1
Name: django-auth-ipwhitelist
Version: 0.1.0
Summary: Django Auth IP Whitelist is a module for identity verification in Django applications, allowing login via IP address and offering whitelist functionality.
Home-page: https://github.com/Skylor-Tang/django-auth-ipwhitelist
Author: tangmeijian
Author-email: tang1996mei@gmail.com
License: BSD license
Keywords: django,django_auth_ipwhitelist,auth,ipwhitelist,whitelist,ip,login
Classifier: Development Status :: 2 - Pre-Alpha
Classifier: Intended Audience :: Developers
Classifier: License :: OSI Approved :: BSD License
Classifier: Natural Language :: English
Classifier: Programming Language :: Python :: 3
Classifier: Programming Language :: Python :: 3.6
Classifier: Programming Language :: Python :: 3.7
Classifier: Programming Language :: Python :: 3.8
Classifier: Programming Language :: Python :: 3.9
Classifier: Programming Language :: Python :: 3.10
Requires-Python: >=3.6
License-File: LICENSE
License-File: AUTHORS.rst
